bigrams/__init__.py
bigrams/bigrams.py
bigrams/py.typed
bigrams-0.1.1.dist-info/WHEEL
bigrams-0.1.1.dist-info/METADATA
bigrams-0.1.1.dist-info/RECORD
