Metadata-Version: 2.1
Name: bigrams
Version: 0.1.1
Summary: Simply create (N)grams
Home-page: https://proteusiq.github.io/bigrams
License: MIT
Author: Prayson W. Daniel
Author-email: praysonpi@gmail.com
Requires-Python: >=3.8.1,<4.0
Classifier: Development Status :: 4 - Beta
Classifier: Intended Audience :: Developers
Classifier: License :: OSI Approved :: MIT License
Classifier: Operating System :: OS Independent
Classifier: Programming Language :: Python
Classifier: Programming Language :: Python :: 3
Classifier: Programming Language :: Python :: 3.9
Classifier: Programming Language :: Python :: 3.10
Classifier: Programming Language :: Python :: 3
Classifier: Programming Language :: Python :: 3.10
Classifier: Programming Language :: Python :: 3.11
Classifier: Programming Language :: Python :: 3.9
Classifier: Topic :: Software Development :: Libraries :: Python Modules
Classifier: Typing :: Typed
Requires-Dist: cytoolz (>=0.12.1,<0.13.0)
Requires-Dist: more-itertools (>=9.0.0,<10.0.0)
Project-URL: Documentation, https://proteusiq.github.io/bigrams
Project-URL: Repository, https://github.com/proteusiq/bigrams
